promptcompression/__init__.py
promptcompression/text_compressor.py
promptcompression-0.1.4.dist-info/METADATA
promptcompression-0.1.4.dist-info/WHEEL
promptcompression-0.1.4.dist-info/licenses/LICENSE
promptcompression-0.1.4.dist-info/RECORD
