Metadata-Version: 2.4
Name: promptcompression
Version: 0.1.4
Summary: Taking text input and compressing it into a smaller representation for cost savings.
Project-URL: Repository, https://github.com/coreymichaud/promptcompression
Author-email: Corey Michaud <cor3y.michaud@gmail.com>
License-Expression: MIT
License-File: LICENSE
Keywords: compression,llm,prompt,savings,tokens
Requires-Python: >=3.8
Requires-Dist: nltk>=3.9
Requires-Dist: tiktoken>=0.9
